mcauth3/__init__.py
mcauth3/mcauth3.py
mcauth3-1.0.1.dist-info/licenses/LICENSE
mcauth3-1.0.1.dist-info/METADATA
mcauth3-1.0.1.dist-info/WHEEL
mcauth3-1.0.1.dist-info/top_level.txt
mcauth3-1.0.1.dist-info/RECORD
