Metadata-Version: 2.4
Name: mcauth3
Version: 1.0.1
Summary: A Minecraft authentication library for Microsoft OAuth 2.0
Author-email: GongSunFangYun <721506497@qq.com>
License: MIT
Project-URL: Repository, https://github.com/GongSunFangYun/mcauth3
Requires-Python: >=3.10
License-File: LICENSE
Requires-Dist: requests~=2.32.5
Dynamic: license-file
